service_identity/__init__.py
service_identity/cryptography.py
service_identity/exceptions.py
service_identity/hazmat.py
service_identity/py.typed
service_identity/pyopenssl.py
service_identity_qpython-24.1.0.dist-info/METADATA
service_identity_qpython-24.1.0.dist-info/WHEEL
service_identity_qpython-24.1.0.dist-info/top_level.txt
service_identity_qpython-24.1.0.dist-info/RECORD
