Metadata-Version: 2.4
Name: service-identity-qpython
Version: 24.1.0
Summary: Service identity verification for pyOpenSSL & cryptography.
Author-email: The QPYPI Team <qpypi@qpython.org>
License: MIT AND (Apache-2.0 OR BSD-2-Clause)
Project-URL: Homepage, https://qpypi.qpython.org/project/service-identity-qpython/
Classifier: Intended Audience :: Developers
Classifier: Intended Audience :: Education
Classifier: Intended Audience :: Information Technology
Classifier: Intended Audience :: End Users/Desktop
Classifier: License :: OSI Approved :: Apache Software License
Classifier: Operating System :: Android
Classifier: Programming Language :: Python
Classifier: Programming Language :: Python :: 3.12
Classifier: Topic :: Software Development
Requires-Python: ==3.12.*
Requires-Dist: attrs>=19.1.0
Requires-Dist: pyasn1-modules
Requires-Dist: pyasn1
Requires-Dist: cryptography-qpython
